{
    "contacto": {
        "email": "andresbarajas202@gmail.com",
        "telefono": "3108583834"
    },
    "perfil_resumen": "RIASCOS\n\nde la producción\nanálisis y mejora de procesos.\nCostos y Activos fijos en la cual\ngenerando informes a gerencia respecto al\nde existencias de los productos en\nde costos para el área de compras y\nel levantamiento de información en\nfichas técnicas de los productos, realizaba\ninformes de gestión, cruces de bases de\ncoordinaba y verificaba el estado del\nuna gestión de calidad al verificar los\nuna conciliación de las existencias y los\nAuxiliar de Auditoría interna, apoyando\nsobre todo lo relacionado con el tema de\nde los procesos de producción,\nde ingresos de materia prima rollos\nLibros, revistas Etc. , Validación\nde la compañía ya sea por cuestiones de\na nivel nacional o exportación,\nde la empresa, realizar inventarios\nme desempeñe como auxiliar de\nque manejaba la compañía, en las\nla calidad del producto si se encontraba\nnotificando las novedades evidenciadas\npara la compañía, realizaba cruces de\ngestión de calidad, levantamiento y\nfunciones Verificar el control de\nlos cargues de mercancía, gestionar y\nprogramar y controlar los procesos para\nde alimentos o arenas, crear codificar\nverificar las ordenes de producción.\nWord, Hojas de cálculo en Google, un buen\nlevantamiento de inventarios, conciliación de\ncomo softwares contables y sus módulos\nANDRES GIOVANNY BARAJAS\nBogotá, Colombia\n57 310 858 3834 andresbarajas202@gmail.com\nAdministración de Empresas actualmente.\nTecnológico en Contabilidad y Finanzas.\nCon conocimiento de la gestión empresarial y la optimización\ncon enfoque de cadena de valor.",
    "experiencia": [
        {
            "empresa": "desarrollaba formulación de procesos operativos y contables de costos,",
            "cargo": "Con capacidad de liderazgo, trabajo en equipo y bajo presión,",
            "fecha_inicio": "2025",
            "fecha_fin": null,
            "duracion_meses": null,
            "responsabilidades": [
                "aumento o disminución de los costos de las materias primas, cantidades",
                "inventario y el costo equivalente de estos productos generaba informes",
                "ventas actualizando los valores de los insumos y producto final, se realizaba",
                "campo de los costos de las materias primas para la elaboración de las",
                "toma física de los inventarios en las diferentes plantas, realización de",
                "datos y apoyo en procesos administrativos y contables Activos y Pasivos ,",
                "inventario para tener un mejor control y estado del inventario, realizando",
                "estados de garantías o pendientes de entregas a los clientes mediante",
                "confirmados de entrega a los clientes.",
                "En Panamericana Formas e Impresos me desempeñe en el cargo de",
                "procesos administrativos y contables, realizando informes de gestión",
                "inventarios, informes de Monetización, verificación del personal, validación",
                "verificación de temas relacionados con propiedad planta y equipo, verificación",
                "de papel, tintas e insumos usados para la elaboración del producto terminado",
                "del ingreso del ingreso y salida de repuestos de las diferentes máquinas",
                "compra, cambio o reparación, verificar procesos de despachos de mercancía",
                "arqueos de caja y recepción de dineros por cobros del uso de una rampa",
                "inventarios, realizando tomas físicas en tiendas propias, CEDI y concesiones",
                "cuales se verificaba las cantidades físicas contra los saldos en el sistema,",
                "apto para la venta, analizar la información recopilada y generar informes",
                "con el fin de mantener el control de los inventarios y disminuir las pérdidas",
                "bases de datos de la información, apoyo en funciones administrativas,",
                "conciliación del inventario.",
                "En gesto agro me desempeño como Auditor interno, realizando las siguientes",
                "ingreso y salidas de Inventario, validar las notas crédito generadas, verificar",
                "organizar los procesos y protocolos para el área de inventarios, organizar,",
                "las tomas físicas de inventarios, validar el ingreso de insumos, importaciones",
                "y notificar al área comercial todo lo relacionado con productos nuevos,",
                "manejo de servicio al cliente, y buen dominio en temas relacionados en",
                "información, manejo de activos fijos y buen dominio de otras herramientas",
                "de inventarios.",
                "Actualmente",
                "Gesto Agro"
            ]
        },
        {
            "empresa": "Realizar",
            "cargo": "Analista de",
            "fecha_inicio": "2022-06",
            "fecha_fin": null,
            "duracion_meses": null,
            "responsabilidades": [
                "Presentar",
                "o dar seguimiento a las novedades de las tiendas",
                "Inventarios, Medisfarma. Bogotá, Colombia.",
                "análisis de los inventarios de las diferentes farmacias.",
                "la toma física de los inventarios de la sede principal.",
                "y ajustar los inventarios de las farmacias",
                "las cuentas de cobro cuando los inventarios tienen diferencias",
                "reportes a gerencia sobre los resultados de los inventarios",
                "ajustes solicitados por las farmacias en el sistema",
                "los estados de activos fijos de la empresa y hacerles seguimientos.",
                "Inventarios, Sutex SAS Bogotá, Colombia.",
                "Toma física de los inventarios en Tiendas.",
                "la toma física de los inventarios de la sede principal.",
                "y ajustar los inventarios realizados.",
                "las cuentas de cobro cuando los inventarios tienen diferencias",
                "reportes a gerencia sobre los resultados de los inventarios",
                "actas de inventario notificando hallazgos importantes de costos sobrantes o faltantes.",
                "Procesos, Colchones Paraíso. Bogotá, Colombia.",
                "la toma física de los inventarios de las diferentes bodegas",
                "y verificar el estado de los inventarios dentro de las bodegas.",
                "la organización e implementación de un proceso de inventario que permitiera tener",
                "orden y control de la mercancía.",
                "el uso e implementación del manejo de Google drive para los diferentes procesos",
                "la compañía.",
                "los costos de mercancía y enviar el reporte actualizado de los costos de los productos.",
                "la actualización de códigos de adci en el drive para que con esta información poder",
                "la descripción, el color de tela y el costo unitario.",
                "reportes de costos por producto para la gerencia y el área comercial."
            ]
        },
        {
            "empresa": "Panamericana Forma e Impresos. Bogotá, Colombia.",
            "cargo": "Auditoría,",
            "fecha_inicio": "2022-03",
            "fecha_fin": null,
            "duracion_meses": null,
            "responsabilidades": [
                "ingreso de materia prima.",
                "ingreso suministros e insumos para la compañía.",
                "Solucionar"
            ]
        },
        {
            "empresa": "Realizar",
            "cargo": "Analista de",
            "fecha_inicio": "2021",
            "fecha_fin": null,
            "duracion_meses": null,
            "responsabilidades": [
                "Julio. 2021 Verificar"
            ]
        },
        {
            "empresa": "Realizar",
            "cargo": "Auxiliar de",
            "fecha_inicio": null,
            "fecha_fin": null,
            "duracion_meses": null,
            "responsabilidades": []
        },
        {
            "empresa": "Realizar",
            "cargo": "Auditor de",
            "fecha_inicio": "2021",
            "fecha_fin": null,
            "duracion_meses": null,
            "responsabilidades": [
                "Organizar",
                "Coordinar",
                "Desempeñar",
                "Verificar"
            ]
        },
        {
            "empresa": "Auxiliar de",
            "cargo": "2019 Auxiliar de",
            "fecha_inicio": "2019",
            "fecha_fin": null,
            "duracion_meses": null,
            "responsabilidades": [
                "Verificación",
                "Validación",
                "a nivel nacional e internacional, revisando los",
                "los vehículos y los papeles de la persona que",
                "de papel reciclable.",
                "despachos durante la noche, así mismo como",
                "en las diferentes áreas de la planta ya sea con el",
                "compañía, verificar los montos de dinero en pesos",
                "teniendo en cuenta los tipos cambios.",
                "de inventarios y posterior realizar cíclicos para",
                "completamente bien para evitar fallos y",
                "respecto al informe final del inventario.",
                "puntos de venta a nivel nacional.",
                "coincida los productos de la caja con el producto",
                "el control de calidad del producto.",
                "el centro de distribución hacia puntos mayoristas,",
                "que llega por garantía.",
                "tiendas y generar informes de resultado.",
                "Conocimiento"
            ]
        },
        {
            "empresa": "Conocimiento\nProfesional\nProfesional\nProfesional\nProfesional\nValidar",
            "cargo": "Profesional",
            "fecha_inicio": null,
            "fecha_fin": null,
            "duracion_meses": null,
            "responsabilidades": []
        },
        {
            "empresa": "Conocimiento\nProfesional\nProfesional\nProfesional\nProfesional\nValidar",
            "cargo": "Profesional",
            "fecha_inicio": null,
            "fecha_fin": null,
            "duracion_meses": null,
            "responsabilidades": []
        },
        {
            "empresa": "Conocimiento\nProfesional\nProfesional\nProfesional\nProfesional\nValidar",
            "cargo": "Profesional",
            "fecha_inicio": null,
            "fecha_fin": null,
            "duracion_meses": null,
            "responsabilidades": []
        },
        {
            "empresa": "Validar los procesos de despachos mercancía",
            "cargo": "Profesional",
            "fecha_inicio": null,
            "fecha_fin": null,
            "duracion_meses": null,
            "responsabilidades": [
                "respectivos documentos de cada cargue,",
                "transporta la mercancía.",
                "Verificar los temas relacionados con la venta",
                "Realizar seguimiento al personal nocturno,",
                "verificar las novedades que se presentaran",
                "personal o con la maquinaria.",
                "Realizar arqueos de caja a los dineros de la",
                "colombianos y validar las diferentes monedas",
                "Realizar acompañamiento a todo el tema",
                "verificar que la información de estos quedara",
                "supuestos en la información generada con"
            ]
        },
        {
            "empresa": "Realizar toma física de inventarios en diferentes",
            "cargo": "Auxiliar de Inventarios, Forus Colombia. Bogotá, Colombia.",
            "fecha_inicio": "2017",
            "fecha_fin": null,
            "duracion_meses": null,
            "responsabilidades": [
                "Validar y revisar el contenido del producto que",
                "Verificar el estado de la mercancía y evaluar",
                "Supervisar el despacho de mercancía desde",
                "Concesiones y Puntos de venta.",
                "Recibir y verificar la devolución de mercancía",
                "Analizar los movimientos de mercancía entre",
                "Generar bases de datos para cruzar información"
            ]
        }
    ],
    "educacion": [
        {
            "titulo": null,
            "institucion": "Corporación",
            "año": "2026"
        },
        {
            "titulo": null,
            "institucion": null,
            "año": "2011"
        }
    ],
    "habilidades": [
        "Idiomas nivel",
        "Español nativo",
        "Microsoft word",
        "Power point",
        "Excel",
        "Google analytics",
        "Google ads",
        "Google drive.",
        "Sistema inventarios agimeld",
        "Sistema inventarios sap businness y one"
    ],
    "skills_detectadas": {
        "tecnicas": [
            "NIA",
            "EXCEL",
            "SAP",
            "AUDITORIA",
            "CONTABILIDAD",
            "COSTOS"
        ],
        "blandas": [
            "Liderazgo",
            "Trabajo en equipo",
            "Organizacion"
        ]
    },
    "cursos": [],
    "referencias": "Sindi Arenas Amiga, Auxiliar de Auditoria,\nPanamericana Celular 57 300 702 5652\nFernando Rocancio Amigo, Auxiliar de Inventarios, Forus\nCelular 57 316 725 6127\nOscar Morales Jefe de Área Costos e Inventarios, Colchones Paraíso.\nCelular 57 311 278 3907\nMaria Angela Suarez jefe de Área, Sutex\nCelular 57 310 280 8248\nagro\nIván Camilo Jaramillo Jefe de Área, Medisfarma\nCelular 57 316 497 5996\nJhon Nelson Tarazona Jefe de área, PasH\nCelular 57 314 232 196\nNicolas Muñoz Jefe de Inventarios, Gesto\nCelular 57 321 206 1337",
    "años_experiencia_total": 0.0,
    "cantidad_empleos": 12
}